{
  "file_path": "/work/external-deps/helix-db/helix-container/src/queries.rs",
  "file_hash": "9f29e6cbb181399f02e370b4094525eb66508b7d",
  "updated_at": "2025-12-26T17:34:24.253607",
  "symbols": {
    "function_config_4": {
      "name": "config",
      "type": "function",
      "start_line": 4,
      "end_line": 6,
      "content_hash": "458d652252287e44a019f05cd87bddd23f9a4683",
      "content": "pub fn config() -> Option<Config> {\n    None\n}",
      "pseudo": "",
      "tags": [],
      "qdrant_ids": []
    }
  }
}